[
  {
    "py/object": "model.contact.Contact",
    "firstname": "",
    "middlename": null,
    "lastname": "",
    "nickname": null,
    "title": null,
    "company": null,
    "address": "",
    "homephone": null,
    "mobilephone": null,
    "workphone": null,
    "fax": null,
    "email": "",
    "email2": null,
    "email3": null,
    "homepage": null,
    "bday": null,
    "bmonth": null,
    "byear": null,
    "aday": null,
    "amonth": null,
    "ayear": null,
    "address2": null,
    "secondaryphone": null,
    "notes": null,
    "id": null,
    "all_phones_from_home_page": null,
    "all_emails_from_home_page": null
  },
  {
    "py/object": "model.contact.Contact",
    "firstname": "firstnameL",
    "middlename": null,
    "lastname": "lastname A",
    "nickname": null,
    "title": null,
    "company": null,
    "address": "addressDsG<u\"",
    "homephone": null,
    "mobilephone": null,
    "workphone": null,
    "fax": null,
    "email": "email/ cp(*Do",
    "email2": null,
    "email3": null,
    "homepage": null,
    "bday": null,
    "bmonth": null,
    "byear": null,
    "aday": null,
    "amonth": null,
    "ayear": null,
    "address2": null,
    "secondaryphone": null,
    "notes": null,
    "id": null,
    "all_phones_from_home_page": null,
    "all_emails_from_home_page": null
  },
  {
    "py/object": "model.contact.Contact",
    "firstname": "firstnamejoY~!",
    "middlename": null,
    "lastname": "lastnameXH? 15",
    "nickname": null,
    "title": null,
    "company": null,
    "address": "addressMP QgIL",
    "homephone": null,
    "mobilephone": null,
    "workphone": null,
    "fax": null,
    "email": "email8/hBxS]fS",
    "email2": null,
    "email3": null,
    "homepage": null,
    "bday": null,
    "bmonth": null,
    "byear": null,
    "aday": null,
    "amonth": null,
    "ayear": null,
    "address2": null,
    "secondaryphone": null,
    "notes": null,
    "id": null,
    "all_phones_from_home_page": null,
    "all_emails_from_home_page": null
  },
  {
    "py/object": "model.contact.Contact",
    "firstname": "firstnameq",
    "middlename": null,
    "lastname": "lastnameSwc1_Qx>>jmS",
    "nickname": null,
    "title": null,
    "company": null,
    "address": "address8mdr$hSc+%@",
    "homephone": null,
    "mobilephone": null,
    "workphone": null,
    "fax": null,
    "email": "email2B3+(",
    "email2": null,
    "email3": null,
    "homepage": null,
    "bday": null,
    "bmonth": null,
    "byear": null,
    "aday": null,
    "amonth": null,
    "ayear": null,
    "address2": null,
    "secondaryphone": null,
    "notes": null,
    "id": null,
    "all_phones_from_home_page": null,
    "all_emails_from_home_page": null
  },
  {
    "py/object": "model.contact.Contact",
    "firstname": "firstnamew^bV",
    "middlename": null,
    "lastname": "lastnameLo~b0m5gl\"e c?g&)s",
    "nickname": null,
    "title": null,
    "company": null,
    "address": "address7j",
    "homephone": null,
    "mobilephone": null,
    "workphone": null,
    "fax": null,
    "email": "emailjar",
    "email2": null,
    "email3": null,
    "homepage": null,
    "bday": null,
    "bmonth": null,
    "byear": null,
    "aday": null,
    "amonth": null,
    "ayear": null,
    "address2": null,
    "secondaryphone": null,
    "notes": null,
    "id": null,
    "all_phones_from_home_page": null,
    "all_emails_from_home_page": null
  },
  {
    "py/object": "model.contact.Contact",
    "firstname": "firstnameWL`\"G7o*",
    "middlename": null,
    "lastname": "lastname<S;9] 07^/N7NoWI5",
    "nickname": null,
    "title": null,
    "company": null,
    "address": "address[<?~j",
    "homephone": null,
    "mobilephone": null,
    "workphone": null,
    "fax": null,
    "email": "emailbFPQm$",
    "email2": null,
    "email3": null,
    "homepage": null,
    "bday": null,
    "bmonth": null,
    "byear": null,
    "aday": null,
    "amonth": null,
    "ayear": null,
    "address2": null,
    "secondaryphone": null,
    "notes": null,
    "id": null,
    "all_phones_from_home_page": null,
    "all_emails_from_home_page": null
  },
  {
    "py/object": "model.contact.Contact",
    "firstname": "firstname]S&p &",
    "middlename": null,
    "lastname": "lastname4$\\E-k)^e>  ",
    "nickname": null,
    "title": null,
    "company": null,
    "address": "addressb -_![",
    "homephone": null,
    "mobilephone": null,
    "workphone": null,
    "fax": null,
    "email": "emaile{)\\QA~.",
    "email2": null,
    "email3": null,
    "homepage": null,
    "bday": null,
    "bmonth": null,
    "byear": null,
    "aday": null,
    "amonth": null,
    "ayear": null,
    "address2": null,
    "secondaryphone": null,
    "notes": null,
    "id": null,
    "all_phones_from_home_page": null,
    "all_emails_from_home_page": null
  },
  {
    "py/object": "model.contact.Contact",
    "firstname": "firstname??4",
    "middlename": null,
    "lastname": "lastnameW we? ",
    "nickname": null,
    "title": null,
    "company": null,
    "address": "addresshst&5*c9]H,",
    "homephone": null,
    "mobilephone": null,
    "workphone": null,
    "fax": null,
    "email": "emailaQ3)h}n_",
    "email2": null,
    "email3": null,
    "homepage": null,
    "bday": null,
    "bmonth": null,
    "byear": null,
    "aday": null,
    "amonth": null,
    "ayear": null,
    "address2": null,
    "secondaryphone": null,
    "notes": null,
    "id": null,
    "all_phones_from_home_page": null,
    "all_emails_from_home_page": null
  },
  {
    "py/object": "model.contact.Contact",
    "firstname": "firstname1 8@S",
    "middlename": null,
    "lastname": "lastnameVTZ=8Q\\ (@2\"uxT?.r",
    "nickname": null,
    "title": null,
    "company": null,
    "address": "address'M",
    "homephone": null,
    "mobilephone": null,
    "workphone": null,
    "fax": null,
    "email": "email< QC8J&&\"",
    "email2": null,
    "email3": null,
    "homepage": null,
    "bday": null,
    "bmonth": null,
    "byear": null,
    "aday": null,
    "amonth": null,
    "ayear": null,
    "address2": null,
    "secondaryphone": null,
    "notes": null,
    "id": null,
    "all_phones_from_home_page": null,
    "all_emails_from_home_page": null
  },
  {
    "py/object": "model.contact.Contact",
    "firstname": "firstnamewwe3n=kd$",
    "middlename": null,
    "lastname": "lastname",
    "nickname": null,
    "title": null,
    "company": null,
    "address": "address}:,%",
    "homephone": null,
    "mobilephone": null,
    "workphone": null,
    "fax": null,
    "email": "email\\=!HW4p]^aU|5m",
    "email2": null,
    "email3": null,
    "homepage": null,
    "bday": null,
    "bmonth": null,
    "byear": null,
    "aday": null,
    "amonth": null,
    "ayear": null,
    "address2": null,
    "secondaryphone": null,
    "notes": null,
    "id": null,
    "all_phones_from_home_page": null,
    "all_emails_from_home_page": null
  },
  {
    "py/object": "model.contact.Contact",
    "firstname": "firstname5",
    "middlename": null,
    "lastname": "lastname%eL",
    "nickname": null,
    "title": null,
    "company": null,
    "address": "addressXFGqkf b3=",
    "homephone": null,
    "mobilephone": null,
    "workphone": null,
    "fax": null,
    "email": "email` &v[*",
    "email2": null,
    "email3": null,
    "homepage": null,
    "bday": null,
    "bmonth": null,
    "byear": null,
    "aday": null,
    "amonth": null,
    "ayear": null,
    "address2": null,
    "secondaryphone": null,
    "notes": null,
    "id": null,
    "all_phones_from_home_page": null,
    "all_emails_from_home_page": null
  }
]